lathiumapi/__init__.py
lathiumapi/myfunctions.py
tests/__init__.py
tests/test_myfunctions.py
lathiumapi-0.0.1.dist-info/METADATA
lathiumapi-0.0.1.dist-info/WHEEL
lathiumapi-0.0.1.dist-info/top_level.txt
lathiumapi-0.0.1.dist-info/RECORD
