Metadata-Version: 2.1
Name: lathiumapi
Version: 0.0.1
Summary: Python Discord Libary for the API of Lathium Tool!
Home-page: UNKNOWN
Author: RequiredHandler
Author-email: noemail@nomail.com
License: UNKNOWN
Keywords: python,lathium,lathiumtool,lathiumsystem,lathiumapi,lathiumdiscord
Platform: UNKNOWN
Classifier: Development Status :: 1 - Planning
Classifier: Intended Audience :: Developers
Classifier: Programming Language :: Python :: 3
Classifier: Operating System :: Unix
Classifier: Operating System :: MacOS :: MacOS X
Classifier: Operating System :: Microsoft :: Windows
Requires-Dist: opencv-python
Requires-Dist: pyautogui
Requires-Dist: pyaudio
